README.md
setup.py
kumquat/__init__.py
kumquat/application.py
kumquat/context.py
kumquat/request.py
kumquat/response.py
kumquat/route.py
kumquat/types.py
kumquat.egg-info/PKG-INFO
kumquat.egg-info/SOURCES.txt
kumquat.egg-info/dependency_links.txt
kumquat.egg-info/requires.txt
kumquat.egg-info/top_level.txt