Metadata-Version: 2.1
Name: kumquat
Version: 0.0.1
Summary: simple web framework with features
Home-page: https://github.com/kesha1225/Kumquat
Author: kesha1225
License: UNKNOWN
Platform: UNKNOWN
